README.md
setup.py
bootstrap3_datetime/__init__.py
bootstrap3_datetime/widgets.py
django_bootstrap3_datetimepicker_3.egg-info/PKG-INFO
django_bootstrap3_datetimepicker_3.egg-info/SOURCES.txt
django_bootstrap3_datetimepicker_3.egg-info/dependency_links.txt
django_bootstrap3_datetimepicker_3.egg-info/top_level.txt